discoIPC/__init__.py
discoIPC/ipc.py
discoIPC-1.0.0.dist-info/DESCRIPTION.rst
discoIPC-1.0.0.dist-info/LICENSE.txt
discoIPC-1.0.0.dist-info/METADATA
discoIPC-1.0.0.dist-info/RECORD
discoIPC-1.0.0.dist-info/WHEEL
discoIPC-1.0.0.dist-info/metadata.json
discoIPC-1.0.0.dist-info/top_level.txt
