Metadata-Version: 1.2
Name: discoIPC
Version: 1.0.0
Summary: Connect to the local Discord IPC Socket, for features like Rich Presence.
Home-page: https://github.com/k3rn31p4nic/discoIPC
Author: k3rn31p4nic
Author-email: UNKNOWN
License: GPL-3.0
Keywords: discord disco discoipc ipc rpc rich-presence presence activity wrapper library
Platform: UNKNOWN
Classifier: Development Status :: 5 - Production/Stable
Classifier: License :: OSI Approved :: GNU General Public License v3 (GPLv3)
Classifier: Intended Audience :: Developers
Classifier: Natural Language :: English
Classifier: Operating System :: OS Independent
Classifier: Programming Language :: Python
Classifier: Programming Language :: Python :: 2.7
Classifier: Programming Language :: Python :: 3.4
Classifier: Topic :: Internet
Classifier: Topic :: Software Development :: Libraries
Classifier: Topic :: Software Development :: Libraries :: Python Modules
Classifier: Topic :: Utilities
Requires-Python: >=2.7, !=3.0.*, !=3.1.*, !=3.2.*, !=3.3.*, <4
